globalign/__init__.py
globalign/conclude.py
globalign/globaligner.py
globalign/start.py
globalign/data/__init__.py
globalign/data/scoring_matrices/BLOSUM50.mtx
globalign/data/scoring_matrices/BLOSUM62.mtx
globalign/data/scoring_matrices/__init__.py
globalign/data/scoring_matrices/nucleotide.mtx
globalign-0.1.16.dist-info/METADATA
globalign-0.1.16.dist-info/WHEEL
globalign-0.1.16.dist-info/entry_points.txt
globalign-0.1.16.dist-info/licenses/LICENSE.txt
globalign-0.1.16.dist-info/RECORD
