Metadata-Version: 2.4
Name: globalign
Version: 0.1.16
Summary: Global Sequence Alignment
Project-URL: Documentation, https://iamgiddyaboutgit.github.io/globalign/
Project-URL: Issues, https://github.com/iamgiddyaboutgit/globalign/issues
Project-URL: Source, https://github.com/iamgiddyaboutgit/globalign
Author: Justin Patterson
License-Expression: MIT
License-File: LICENSE.txt
Keywords: Global Sequence Alignment,Needleman–Wunsch,alignment,bioinformatics,sequence,sequence alignment
Classifier: Development Status :: 3 - Alpha
Classifier: Natural Language :: English
Classifier: Programming Language :: Python
Classifier: Programming Language :: Python :: 3.10
Classifier: Programming Language :: Python :: 3.11
Classifier: Programming Language :: Python :: 3.12
Classifier: Programming Language :: Python :: Implementation :: CPython
Classifier: Programming Language :: Python :: Implementation :: PyPy
Classifier: Topic :: Scientific/Engineering :: Bio-Informatics
Requires-Python: >=3.10
